callbaker/__init__.py
callbaker/functions.py
callbaker-1.4.0.dist-info/LICENSE
callbaker-1.4.0.dist-info/METADATA
callbaker-1.4.0.dist-info/WHEEL
callbaker-1.4.0.dist-info/top_level.txt
callbaker-1.4.0.dist-info/RECORD
