Metadata-Version: 2.1
Name: callbaker
Version: 1.4.0
Summary: Telegram Button Callback Data Converter
Home-page: https://github.com/torrua/callbaker
Author: torrua
Author-email: torrua@gmail.com
License: MIT
Download-URL: https://github.com/torrua/callbaker/archive/v1.4.0.tar.gz
Keywords: Convert,Callback,Keyboard,Telegram,Inline
Platform: UNKNOWN
Classifier: Development Status :: 4 - Beta
Classifier: Intended Audience :: Developers
Classifier: Topic :: Software Development :: Build Tools
Classifier: License :: OSI Approved :: MIT License
Classifier: Programming Language :: Python :: 3.6
Classifier: Programming Language :: Python :: 3.7
Classifier: Programming Language :: Python :: 3.8
Classifier: Programming Language :: Python :: 3.9
Requires-Python: >=3.6
